birder/__init__.py
birder/admin.py
birder/apps.py
birder/check.py
birder/context_processors.py
birder/db.py
birder/exceptions.py
birder/forms.py
birder/handlers.py
birder/models.py
birder/signals.py
birder/tasks.py
birder/types.pyi
birder/version.py
birder/views.py
birder/checks/__init__.py
birder/checks/amqp.py
birder/checks/base.py
birder/checks/celery.py
birder/checks/dns.py
birder/checks/elastic_search.py
birder/checks/ftp.py
birder/checks/http.py
birder/checks/json.py
birder/checks/ldap.py
birder/checks/memcache.py
birder/checks/minio.py
birder/checks/mysql.py
birder/checks/passive.py
birder/checks/pg.py
birder/checks/redis.py
birder/checks/registry.py
birder/checks/s3.py
birder/checks/smtp.py
birder/checks/ssh.py
birder/checks/tcp.py
birder/checks/xml.py
birder/cli/__init__.py
birder/cli/bg.py
birder/cli/check.py
birder/cli/deadlines.py
birder/cli/env.py
birder/cli/monitor.py
birder/cli/upgrade.py
birder/config/__init__.py
birder/config/asgi.py
birder/config/console.py
birder/config/settings.py
birder/config/urls.py
birder/config/wsgi.py
birder/config/fragments/__init__.py
birder/config/fragments/app.py
birder/config/fragments/constance.py
birder/config/fragments/crypt.py
birder/config/fragments/dramatiq.py
birder/config/fragments/sentry.py
birder/config/fragments/social_auth.py
birder/config/fragments/tailwind.py
birder/config/fragments/unfold.py
birder/console/__init__.py
birder/console/site.py
birder/locale/ar/LC_MESSAGES/django.mo
birder/locale/ar/LC_MESSAGES/django.po
birder/locale/en/LC_MESSAGES/django.mo
birder/locale/en/LC_MESSAGES/django.po
birder/locale/es/LC_MESSAGES/django.mo
birder/locale/es/LC_MESSAGES/django.po
birder/locale/fr/LC_MESSAGES/django.mo
birder/locale/fr/LC_MESSAGES/django.po
birder/locale/it/LC_MESSAGES/django.mo
birder/locale/it/LC_MESSAGES/django.po
birder/management/__init__.py
birder/management/commands/__init__.py
birder/management/commands/demo.py
birder/migrations/0001_initial.py
os4d_birder-2.5.dist-info/METADATA
os4d_birder-2.5.dist-info/WHEEL
os4d_birder-2.5.dist-info/entry_points.txt
os4d_birder-2.5.dist-info/licenses/LICENSE
os4d_birder-2.5.dist-info/RECORD
