Metadata-Version: 2.4
Name: os4d-birder
Version: 2.5
Summary: Healthcheck and uptime system monitoring platform
Project-URL: Docker Image, https://hub.docker.com/repository/docker/os4d/birder/general
Project-URL: Documentation, https://os4d.github.io/birder/
Project-URL: Homepage, https://github.com/os4d/birder
Project-URL: Issues, https://github.com/ os4d/birder/issues
Project-URL: Pypi Home, https://pypi.org/project/os4d-birder/
Project-URL: Repository, https://github.com/os4d/birder
Author-email: mark <hanarero@gmail.com>, sax <s.apostolico@gmail.com>
License: MIT
License-File: LICENSE
Classifier: Programming Language :: Python :: 3 :: Only
Classifier: Programming Language :: Python :: 3.12
Requires-Python: ==3.12.*
Requires-Dist: attrs>=24.3
Requires-Dist: beautifulsoup4>=4.12.3
Requires-Dist: bitarray>=3
Requires-Dist: boto3>=1.35.90
Requires-Dist: celery>=5.4
Requires-Dist: channels-redis>=4.2.1
Requires-Dist: channels>=4.2
Requires-Dist: circus>=0.18
Requires-Dist: click>=8.1.8
Requires-Dist: daphne>=4.1.2
Requires-Dist: django-admin-extra-buttons>=1.6
Requires-Dist: django-adminfilters>=2.5.2
Requires-Dist: django-constance>=4.1.3
Requires-Dist: django-csp>=3.8
Requires-Dist: django-dramatiq>=0.12
Requires-Dist: django-environ>=0.11.2
Requires-Dist: django-fernet-encrypted-fields>=0.3
Requires-Dist: django-flags>=5.0.13
Requires-Dist: django-markdown-deux>=1.0.6
Requires-Dist: django-recurrence>=1.11.1
Requires-Dist: django-redis>=5.4
Requires-Dist: django-regex>=0.5
Requires-Dist: django-strategy-field>=3.1
Requires-Dist: django-stubs>=5.2
Requires-Dist: django-tailwind>=4
Requires-Dist: django-timezone-field>=7
Requires-Dist: django-unfold>=0.60
Requires-Dist: django>=5.2
Requires-Dist: djangorestframework>=3.15.2
Requires-Dist: dnspython>=2.6.1
Requires-Dist: dramatiq-crontab[sentry]>=1.0.8
Requires-Dist: dramatiq>=1.17.1
Requires-Dist: durations-nlp>=1.0.1
Requires-Dist: elasticsearch>=9.0.2
Requires-Dist: flower>=2.0.1
Requires-Dist: jmespath>=1.0.1
Requires-Dist: kombu>=5.4.2
Requires-Dist: ldap3>=2.9.1
Requires-Dist: lxml>=5.3
Requires-Dist: minio>=7.2.13
Requires-Dist: pandas<2.3
Requires-Dist: pexpect>=4.9
Requires-Dist: pip>=24.3.1
Requires-Dist: prometheus-client==0.20
Requires-Dist: psycopg2-binary>=2.9.10
Requires-Dist: pymemcache>=4
Requires-Dist: pymysql>=1.1.1
Requires-Dist: python-redis-lock[django]>=4
Requires-Dist: pytz>=2024.2
Requires-Dist: redis-timeseries>=0.1.9
Requires-Dist: redis>=5.2.1
Requires-Dist: requests>=2.32.3
Requires-Dist: sentry-sdk>=2.19.2
Requires-Dist: social-auth-app-django>=5.4.2
Requires-Dist: tabulate>=0.9
